LICENSE
MANIFEST.in
README.md
abspath.py
requirements.txt
setup.py
python_abspath.egg-info/PKG-INFO
python_abspath.egg-info/SOURCES.txt
python_abspath.egg-info/dependency_links.txt
python_abspath.egg-info/entry_points.txt
python_abspath.egg-info/not-zip-safe
python_abspath.egg-info/requires.txt
python_abspath.egg-info/top_level.txt