Metadata-Version: 2.1
Name: python-abspath
Version: 0.1.1
Summary: python-abspath provides a command line tool that prints the absolute paths of all given files. File names can be piped via STDIN or given as arguments. Work for both Windows and Linux.
Home-page: https://github.com/zencore-cn/zencore-issues
Author: zencore
Author-email: dobetter@zencore.cn
License: MIT
Keywords: command line utils,python-abspath
Platform: UNKNOWN
Classifier: Development Status :: 5 - Production/Stable
Classifier: Intended Audience :: Developers
Classifier: Topic :: Software Development :: Libraries :: Python Modules
Classifier: License :: OSI Approved :: MIT License
Classifier: Programming Language :: Python :: 3
Classifier: Programming Language :: Python :: 3 :: Only
